.gitignore
LICENSE
README.md
Singularity_elikopy
code_sructure.txt
folder_structure.txt
requirements.txt
setup.cfg
setup.py
docs/LICENSE
docs/Makefile
docs/conf.py
docs/contributing.rst
docs/elikopy.rst
docs/elikopy_project.rst
docs/elikopy_usage.rst
docs/examples.rst
docs/favicon.png
docs/index.rst
docs/installation.rst
docs/introduction.rst
docs/license.rst
docs/logo.png
docs/make.bat
docs/metrics.rst
docs/other_data.rst
docs/other_utils.rst
docs/preprocessing_T1.rst
docs/preprocessing_dmri.rst
docs/stats_other.rst
docs/stats_tbss.rst
docs/pictures/folder_structure.jpg
docs/pictures/pipeline_steps.jpg
docs/pictures/preproc_bet.jpg
docs/pictures/preproc_gibbs.jpg
docs/pictures/preproc_mppca.jpg
docs/pictures/preprocessing.PNG
docs/pictures/root.png
elikopy/__init__.py
elikopy/core.py
elikopy/individual_subject_processing.py
elikopy/modelSynb0Disco.py
elikopy/utils.py
elikopy/utilsSynb0Disco.py
elikopy.egg-info/PKG-INFO
elikopy.egg-info/SOURCES.txt
elikopy.egg-info/dependency_links.txt
elikopy.egg-info/requires.txt
elikopy.egg-info/top_level.txt